aws_cdk_code_builder/__init__.py
tests/__init__.py
tests/test_build.py
aws_cdk_code_builder-1.2.4.dist-info/LICENSE
aws_cdk_code_builder-1.2.4.dist-info/METADATA
aws_cdk_code_builder-1.2.4.dist-info/WHEEL
aws_cdk_code_builder-1.2.4.dist-info/top_level.txt
aws_cdk_code_builder-1.2.4.dist-info/RECORD
