Metadata-Version: 2.1
Name: aws-cdk-code-builder
Version: 1.2.4
Summary: A Library that extends the aws_lambda.Code.from_asset and allows for auto packaging of the project
Home-page: https://github.com/DEADSEC-SECURITY/aws-cdk-code-builder
Author: DeadSec-Security
Author-email: amng835@gmail.com
Keywords: aws_cdk,aws_cdk_build,aws_cdk_packaging
Requires-Python: >=3.7
License-File: LICENSE
Requires-Dist: aws-cdk-lib (>=2.50.0)
